[
    {
        "name": "Rueben Bain Jr.",
        "position": "EDGE",
        "team": "Miami",
        "stats": {
            "height": "6'3\"",
            "weight": "275",
            "40Time": "N/A"
        },
        "rating": 1,
        "scoutingReport": ""
    },
    {
        "name": "Caleb Downs",
        "position": "S",
        "team": "Ohio State",
        "stats": {
            "height": "6'0\"",
            "weight": "205",
            "40Time": "N/A"
        },
        "rating": 2,
        "scoutingReport": ""
    },
    {
        "name": "Arvell Reese",
        "position": "LB",
        "team": "Ohio State",
        "stats": {
            "height": "6'4\"",
            "weight": "243",
            "40Time": "N/A"
        },
        "rating": 3,
        "scoutingReport": ""
    },
    {
        "name": "Fernando Mendoza",
        "position": "QB",
        "team": "Indiana",
        "stats": {
            "height": "6'5\"",
            "weight": "225",
            "40Time": "N/A"
        },
        "rating": 4,
        "scoutingReport": ""
    },
    {
        "name": "Jordyn Tyson",
        "position": "WR",
        "team": "Arizona State",
        "stats": {
            "height": "6'2\"",
            "weight": "195",
            "40Time": "N/A"
        },
        "rating": 5,
        "scoutingReport": ""
    },
    {
        "name": "Peter Woods",
        "position": "DL",
        "team": "Clemson",
        "stats": {
            "height": "6'3\"",
            "weight": "315",
            "40Time": "N/A"
        },
        "rating": 6,
        "scoutingReport": ""
    },
    {
        "name": "Ty Simpson",
        "position": "QB",
        "team": "Alabama",
        "stats": {
            "height": "6'2\"",
            "weight": "208",
            "40Time": "N/A"
        },
        "rating": 7,
        "scoutingReport": ""
    },
    {
        "name": "Spencer Fano",
        "position": "OT",
        "team": "Utah",
        "stats": {
            "height": "6'6\"",
            "weight": "302",
            "40Time": "N/A"
        },
        "rating": 8,
        "scoutingReport": ""
    },
    {
        "name": "Keldric Faulk",
        "position": "EDGE",
        "team": "Auburn",
        "stats": {
            "height": "6'6\"",
            "weight": "270",
            "40Time": "N/A"
        },
        "rating": 9,
        "scoutingReport": ""
    },
    {
        "name": "Carnell Tate",
        "position": "WR",
        "team": "Ohio State",
        "stats": {
            "height": "6'3\"",
            "weight": "191",
            "40Time": "N/A"
        },
        "rating": 10,
        "scoutingReport": ""
    },
    {
        "name": "Dante Moore",
        "position": "QB",
        "team": "Oregon",
        "stats": {
            "height": "6'3\"",
            "weight": "206",
            "40Time": "N/A"
        },
        "rating": 11,
        "scoutingReport": ""
    },
    {
        "name": "Jeremiyah Love",
        "position": "RB",
        "team": "Notre Dame",
        "stats": {
            "height": "6'0\"",
            "weight": "214",
            "40Time": "N/A"
        },
        "rating": 12,
        "scoutingReport": ""
    },
    {
        "name": "Francis Mauigoa",
        "position": "OT",
        "team": "Miami",
        "stats": {
            "height": "6'6\"",
            "weight": "335",
            "40Time": "N/A"
        },
        "rating": 13,
        "scoutingReport": ""
    },
    {
        "name": "Mansoor Delane",
        "position": "CB",
        "team": "LSU",
        "stats": {
            "height": "6'1\"",
            "weight": "187",
            "40Time": "N/A"
        },
        "rating": 14,
        "scoutingReport": ""
    },
    {
        "name": "Jermod McCoy",
        "position": "CB",
        "team": "Tennessee",
        "stats": {
            "height": "6'0\"",
            "weight": "193",
            "40Time": "N/A"
        },
        "rating": 15,
        "scoutingReport": ""
    },
    {
        "name": "David Bailey",
        "position": "EDGE",
        "team": "Texas Tech",
        "stats": {
            "height": "6'3\"",
            "weight": "250",
            "40Time": "N/A"
        },
        "rating": 16,
        "scoutingReport": ""
    },
    {
        "name": "Kadyn Proctor",
        "position": "OT",
        "team": "Alabama",
        "stats": {
            "height": "6'7\"",
            "weight": "366",
            "40Time": "N/A"
        },
        "rating": 17,
        "scoutingReport": ""
    },
    {
        "name": "Kenyon Sadiq",
        "position": "TE",
        "team": "Oregon",
        "stats": {
            "height": "6'3\"",
            "weight": "245",
            "40Time": "N/A"
        },
        "rating": 18,
        "scoutingReport": ""
    },
    {
        "name": "Avieon Terrell",
        "position": "CB",
        "team": "Clemson",
        "stats": {
            "height": "5'11\"",
            "weight": "180",
            "40Time": "N/A"
        },
        "rating": 19,
        "scoutingReport": ""
    },
    {
        "name": "T.J. Parker",
        "position": "EDGE",
        "team": "Clemson",
        "stats": {
            "height": "6'3\"",
            "weight": "265",
            "40Time": "N/A"
        },
        "rating": 20,
        "scoutingReport": ""
    },
    {
        "name": "Makai Lemon",
        "position": "WR",
        "team": "USC",
        "stats": {
            "height": "5'11\"",
            "weight": "195",
            "40Time": "N/A"
        },
        "rating": 21,
        "scoutingReport": ""
    },
    {
        "name": "Denzel Boston",
        "position": "WR",
        "team": "Washington",
        "stats": {
            "height": "6'4\"",
            "weight": "209",
            "40Time": "N/A"
        },
        "rating": 22,
        "scoutingReport": ""
    },
    {
        "name": "Sonny Styles",
        "position": "LB",
        "team": "Ohio State",
        "stats": {
            "height": "6'4\"",
            "weight": "235",
            "40Time": "N/A"
        },
        "rating": 23,
        "scoutingReport": ""
    },
    {
        "name": "Caleb Lomu",
        "position": "OT",
        "team": "Utah",
        "stats": {
            "height": "6'6\"",
            "weight": "304",
            "40Time": "N/A"
        },
        "rating": 24,
        "scoutingReport": ""
    },
    {
        "name": "Cashius Howell",
        "position": "EDGE",
        "team": "Texas A&M",
        "stats": {
            "height": "6'2\"",
            "weight": "248",
            "40Time": "N/A"
        },
        "rating": 25,
        "scoutingReport": ""
    },
    {
        "name": "Vega Ioane",
        "position": "IOL",
        "team": "Penn State",
        "stats": {
            "height": "6'4\"",
            "weight": "328",
            "40Time": "N/A"
        },
        "rating": 26,
        "scoutingReport": ""
    },
    {
        "name": "CJ Allen",
        "position": "LB",
        "team": "Georgia",
        "stats": {
            "height": "6'1\"",
            "weight": "235",
            "40Time": "N/A"
        },
        "rating": 27,
        "scoutingReport": ""
    },
    {
        "name": "Matayo Uiagalelei",
        "position": "EDGE",
        "team": "Oregon",
        "stats": {
            "height": "6'5\"",
            "weight": "270",
            "40Time": "N/A"
        },
        "rating": 28,
        "scoutingReport": ""
    },
    {
        "name": "Chris Bell",
        "position": "WR",
        "team": "Louisville",
        "stats": {
            "height": "6'2\"",
            "weight": "220",
            "40Time": "N/A"
        },
        "rating": 29,
        "scoutingReport": ""
    },
    {
        "name": "Colton Hood",
        "position": "CB",
        "team": "Tennessee",
        "stats": {
            "height": "6'0\"",
            "weight": "195",
            "40Time": "N/A"
        },
        "rating": 30,
        "scoutingReport": ""
    },
    {
        "name": "Caleb Banks",
        "position": "DL",
        "team": "Florida",
        "stats": {
            "height": "6'6\"",
            "weight": "329",
            "40Time": "N/A"
        },
        "rating": 31,
        "scoutingReport": ""
    },
    {
        "name": "Anthony Hill Jr.",
        "position": "LB",
        "team": "Texas",
        "stats": {
            "height": "6'3\"",
            "weight": "235",
            "40Time": "N/A"
        },
        "rating": 32,
        "scoutingReport": ""
    },
    {
        "name": "LT Overton",
        "position": "EDGE",
        "team": "Alabama",
        "stats": {
            "height": "6'5\"",
            "weight": "283",
            "40Time": "N/A"
        },
        "rating": 33,
        "scoutingReport": ""
    },
    {
        "name": "KC Concepcion",
        "position": "WR",
        "team": "Texas A&M",
        "stats": {
            "height": "5'11\"",
            "weight": "190",
            "40Time": "N/A"
        },
        "rating": 34,
        "scoutingReport": ""
    },
    {
        "name": "A'Mauri Washington",
        "position": "DL",
        "team": "Oregon",
        "stats": {
            "height": "6'3\"",
            "weight": "330",
            "40Time": "N/A"
        },
        "rating": 35,
        "scoutingReport": ""
    },
    {
        "name": "Chris Brazzell II",
        "position": "WR",
        "team": "Tennessee",
        "stats": {
            "height": "6'5\"",
            "weight": "200",
            "40Time": "N/A"
        },
        "rating": 36,
        "scoutingReport": ""
    },
    {
        "name": "R Mason Thomas",
        "position": "EDGE",
        "team": "Oklahoma",
        "stats": {
            "height": "6'2\"",
            "weight": "249",
            "40Time": "N/A"
        },
        "rating": 37,
        "scoutingReport": ""
    },
    {
        "name": "LaNorris Sellers",
        "position": "QB",
        "team": "South Carolina",
        "stats": {
            "height": "6'3\"",
            "weight": "240",
            "40Time": "N/A"
        },
        "rating": 38,
        "scoutingReport": ""
    },
    {
        "name": "Kayden McDonald",
        "position": "DL",
        "team": "Ohio State",
        "stats": {
            "height": "6'3\"",
            "weight": "326",
            "40Time": "N/A"
        },
        "rating": 39,
        "scoutingReport": ""
    },
    {
        "name": "Christen Miller",
        "position": "DL",
        "team": "Georgia",
        "stats": {
            "height": "6'4\"",
            "weight": "305",
            "40Time": "N/A"
        },
        "rating": 40,
        "scoutingReport": ""
    },
    {
        "name": "Dillon Thieneman",
        "position": "S",
        "team": "Oregon",
        "stats": {
            "height": "6'0\"",
            "weight": "207",
            "40Time": "N/A"
        },
        "rating": 41,
        "scoutingReport": ""
    },
    {
        "name": "Gennings Dunker",
        "position": "OT",
        "team": "Iowa",
        "stats": {
            "height": "6'5\"",
            "weight": "316",
            "40Time": "N/A"
        },
        "rating": 42,
        "scoutingReport": ""
    },
    {
        "name": "Quincy Rhodes Jr.",
        "position": "EDGE",
        "team": "Arkansas",
        "stats": {
            "height": "6'6\"",
            "weight": "275",
            "40Time": "N/A"
        },
        "rating": 43,
        "scoutingReport": ""
    }
]